libs/__init__.py
libs/decorators.py
libs/defaults.py
libs/dummy.py
libs/dummy_data.py
libs/logs.py
libs/messages.py
libs/perms.py
libs/validaitons.py
mruus_lib-0.1.0.dist-info/METADATA
mruus_lib-0.1.0.dist-info/WHEEL
mruus_lib-0.1.0.dist-info/top_level.txt
mruus_lib-0.1.0.dist-info/RECORD
